CONTRIBUTORS
LICENSE
MANIFEST.in
README.rst
setup.py
tox.ini
moneyed/__init__.py
moneyed/classes.py
moneyed/localization.py
moneyed/test_moneyed_classes.py
ud_py_moneyed.egg-info/PKG-INFO
ud_py_moneyed.egg-info/SOURCES.txt
ud_py_moneyed.egg-info/dependency_links.txt
ud_py_moneyed.egg-info/requires.txt
ud_py_moneyed.egg-info/top_level.txt