Metadata-Version: 1.1
Name: ud-py-moneyed
Version: 0.6.2
Summary: Provides Currency and Money classes for use in your Python code.
Home-page: https://github.com/udemy/py-moneyed
Author: UNKNOWN
Author-email: UNKNOWN
License: BSD
Keywords: money currency class abstraction
Platform: UNKNOWN
Classifier: Programming Language :: Python
Classifier: Programming Language :: Python :: 3
Classifier: License :: OSI Approved :: BSD License
Classifier: Operating System :: OS Independent
Classifier: Development Status :: 3 - Alpha
Classifier: Environment :: Other Environment
Classifier: Intended Audience :: Developers
Classifier: Topic :: Office/Business :: Financial
Classifier: Topic :: Software Development :: Libraries :: Python Modules
